tsvector_field/__init__.py
tsvector_field/apps.py
tsvector_field/fields.py
tsvector_field/operations.py
tsvector_field/query.py
tsvector_field/receivers.py
tsvector_field/schema.py
django_tsvector_field-0.9.5.dist-info/LICENSE
django_tsvector_field-0.9.5.dist-info/METADATA
django_tsvector_field-0.9.5.dist-info/WHEEL
django_tsvector_field-0.9.5.dist-info/top_level.txt
django_tsvector_field-0.9.5.dist-info/RECORD
