Metadata-Version: 2.1
Name: django-tsvector-field
Version: 0.9.5
Summary: Django field implementation for PostgreSQL tsvector.
Home-page: https://github.com/damoti/django-tsvector-field
Author: Lex Berezhny
Author-email: lex@damoti.com
License: BSD
Keywords: django,postgres
Platform: UNKNOWN
Classifier: Framework :: Django
Classifier: Intended Audience :: Developers
Classifier: License :: OSI Approved :: BSD License
Classifier: Programming Language :: Python :: 3
Classifier: Operating System :: OS Independent
Classifier: Topic :: Database
Classifier: Topic :: Software Development :: Libraries :: Python Modules
